{
    "title": "mojo.db.sql.SubqueryExpr",
    "description": "",
    "allOf": [
        {
            "$ref": "#/components/schemas/mojo.lang.Expr"
        },
        {
            "title": "mojo.db.sql.SubqueryExpr",
            "type": "object",
            "properties": {
                "exists": {
                    "title": "mojo.core.Bool",
                    "type": "boolean"
                },
                "query": {
                    "$ref": "#/components/schemas/mojo.db.sql.SelectStmt"
                }
            }
        }
    ]
}